hsm_orchestrator/__init__.py
hsm_orchestrator/exceptions.py
hsm_orchestrator/overrides.py
hsm_orchestrator/validators.py
hsm_orchestrator-1.2.0.dist-info/METADATA
hsm_orchestrator-1.2.0.dist-info/WHEEL
hsm_orchestrator-1.2.0.dist-info/entry_points.txt
hsm_orchestrator-1.2.0.dist-info/licenses/LICENSE.txt
hsm_orchestrator-1.2.0.dist-info/RECORD
