Metadata-Version: 2.4
Name: hsm-orchestrator
Version: 1.2.0
Summary: Orchestration tool for Mozilla's offline HSM which facilitates conveying a CSR to the air gapped HSM server
Project-URL: Homepage, https://github.com/mozilla/hsm-orchestrator
Project-URL: Bug Reports, https://github.com/mozilla/hsm-orchestrator/issues
Project-URL: Funding, https://donate.mozilla.org
Project-URL: Say Thanks!, https://saythanks.io/to/gene1wood
Project-URL: Source, https://github.com/mozilla/hsm-orchestrator
Author-email: Gene Wood <gene@mozilla.com>
Maintainer-email: Mozilla Infrastructure Security <security@mozilla.com>
License: Mozilla Public License Version 2.0
License-File: LICENSE.txt
Keywords: hsm
Classifier: Development Status :: 3 - Alpha
Classifier: Intended Audience :: Information Technology
Classifier: Intended Audience :: System Administrators
Classifier: License :: OSI Approved :: Mozilla Public License 2.0 (MPL 2.0)
Classifier: Programming Language :: Python :: 3
Classifier: Programming Language :: Python :: 3 :: Only
Classifier: Programming Language :: Python :: 3.10
Classifier: Programming Language :: Python :: 3.11
Classifier: Programming Language :: Python :: 3.12
Classifier: Programming Language :: Python :: 3.13
Classifier: Programming Language :: Python :: 3.14
Classifier: Topic :: Security
Classifier: Topic :: Security :: Cryptography
Requires-Python: >=3.10
Requires-Dist: click~=8.3.0
Requires-Dist: configobj~=5.0.9
Requires-Dist: gitpython~=3.1.45
Requires-Dist: platformdirs~=4.4.0
Requires-Dist: psutil~=7.1.0
Requires-Dist: rich~=14.1.0
Provides-Extra: test
Requires-Dist: click~=8.3.0; extra == 'test'
Requires-Dist: coverage~=7.10.6; extra == 'test'
Requires-Dist: pytest-datafiles~=3.0.0; extra == 'test'
Requires-Dist: pytest~=8.4.2; extra == 'test'
